Metadata-Version: 1.1
Name: create-django-app
Version: 0.0.9
Summary: CLI tool to automate initialization of Django project
Home-page: https://github.com/arsenlosenko/create-django-app
Author: Arsen Losenko
Author-email: arsenlosenko@gmail.com
License: MIT
Keywords: python django cli CLI
Platform: UNKNOWN
Classifier: Development Status :: 3 - Alpha
Classifier: Intended Audience :: Developers
Classifier: Topic :: Utilities
Classifier: License :: OSI Approved :: MIT License
Classifier: Programming Language :: Python :: 3.5
